ZAminofix/__init__.py
ZAminofix/acm.py
ZAminofix/client.py
ZAminofix/sub_client.py
ZAminofix/lib/__init__.py
ZAminofix/lib/util/__init__.py
ZAminofix/lib/util/exceptions.py
ZAminofix/lib/util/headers.py
ZAminofix/lib/util/helpers.py
ZAminofix/lib/util/objects.py
ZAminofix/ws/__init__.py
ZAminofix/ws/events.py
ZAminofix/ws/handler.py
zamino_fix-1.2.4.dist-info/licenses/LICENSE
zamino_fix-1.2.4.dist-info/METADATA
zamino_fix-1.2.4.dist-info/WHEEL
zamino_fix-1.2.4.dist-info/top_level.txt
zamino_fix-1.2.4.dist-info/RECORD
