Metadata-Version: 2.4
Name: ZAmino.fix
Version: 1.2.4
Summary: ZAmino.fix is a modern and optimized fork of amino.fix, designed for building Amino bots, automations, and custom clients with ease and performance in mind.
Author: ZOOM
Keywords: ZAmino,ZAmino.fix,aminoapps,ZAminofix,amino,amino-bot
Classifier: Development Status :: 4 - Beta
Classifier: Programming Language :: Python :: 3
Classifier: License :: OSI Approved :: MIT License
Classifier: Operating System :: OS Independent
Requires-Python: >=3.6
License-File: LICENSE
Requires-Dist: httpx==0.28.1
Requires-Dist: websocket-client==1.3.1
Requires-Dist: json_minify
Requires-Dist: six
Requires-Dist: websockets
Dynamic: author
Dynamic: classifier
Dynamic: description
Dynamic: description-content-type
Dynamic: keywords
Dynamic: license-file
Dynamic: requires-dist
Dynamic: requires-python
Dynamic: summary
